{
	"info": {
		"_postman_id": "4f2fa860-0aa2-451d-ad7d-1f4a961236ff",
		"name": "go-nats",
		"schema": "https://schema.getpostman.com/json/collection/v2.1.0/collection.json"
	},
	"item": [
		{
			"name": "Publisher API",
			"request": {
				"method": "POST",
				"header": [],
				"body": {
					"mode": "raw",
					"raw": "{\n    \"message\": \"HELLO WORLD\"\n}\n",
					"options": {
						"raw": {
							"language": "json"
						}
					}
				},
				"url": {
					"raw": "http://localhost:9090/api/publish-subscribe",
					"protocol": "http",
					"host": [
						"localhost"
					],
					"port": "9090",
					"path": [
						"api",
						"publish-subscribe"
					]
				}
			},
			"response": []
		}
	],
	"protocolProfileBehavior": {}
}